brightsky/__init__.py
brightsky/__main__.py
brightsky/cli.py
brightsky/db.py
brightsky/enhancements.py
brightsky/export.py
brightsky/parsers.py
brightsky/polling.py
brightsky/query.py
brightsky/settings.py
brightsky/tasks.py
brightsky/utils.py
brightsky/worker.py
brightsky/web/__init__.py
brightsky/web/app.py
brightsky/web/models.py
brightsky/web/params.py
brightsky-2.2.7.dist-info/licenses/LICENSE
brightsky-2.2.7.dist-info/METADATA
brightsky-2.2.7.dist-info/WHEEL
brightsky-2.2.7.dist-info/top_level.txt
brightsky-2.2.7.dist-info/RECORD
