Metadata-Version: 2.4
Name: brightsky
Version: 2.2.7
Summary: JSON API for DWD's open weather data.
Author-email: Jakob de Maeyer <jakob@brightsky.dev>
License: MIT
Project-URL: Homepage, https://brightsky.dev/
Project-URL: Documentation, https://brightsky.dev/docs/
Project-URL: Source, https://github.com/jdemaeyer/brightsky/
Project-URL: Tracker, https://github.com/jdemaeyer/brightsky/issues/
Classifier: Programming Language :: Python :: 3
Classifier: License :: OSI Approved :: MIT License
Classifier: Operating System :: OS Independent
Requires-Python: >=3.8
License-File: LICENSE
Requires-Dist: astral
Requires-Dist: asyncpg
Requires-Dist: click
Requires-Dist: coloredlogs
Requires-Dist: dwdparse[all]
Requires-Dist: falcon>=3
Requires-Dist: fastapi
Requires-Dist: gunicorn
Requires-Dist: httpx
Requires-Dist: huey
Requires-Dist: isal
Requires-Dist: numpy
Requires-Dist: orjson
Requires-Dist: parsel
Requires-Dist: psycopg2-binary
Requires-Dist: pyproj
Requires-Dist: python-dateutil
Requires-Dist: redis
Requires-Dist: requests
Requires-Dist: sentry-sdk
Requires-Dist: shapely
Requires-Dist: uvicorn
Dynamic: license-file
